{"contact_email":"demand@synacor.com","contact_address":"40 La Riviere Dr #300, Buffalo, NY 14202","version":"1.0","identifiers":[{"name":"TAG-ID","value":"e108f11b2cdf7d5b"}],"sellers":[{"seller_id":53,"seller_type":"PUBLISHER","name":"Chill Out Point","domain":"chilloutpoint.com"},{"seller_id":1931,"seller_type":"BOTH","name":"FinancialContent Services, Inc","domain":"financialcontent.com"},{"seller_id":10567,"seller_type":"PUBLISHER","name":"PsOug.org","domain":"psoug.org"},{"seller_id":10977,"seller_type":"PUBLISHER","name":"Stephanie Lynn","domain":"bystephanielynn.com"},{"seller_id":13321,"seller_type":"PUBLISHER","name":"Get A Copywriter Inc.","domain":"getacopywriter.com"},{"seller_id":81201,"seller_type":"PUBLISHER","name":"CenturyLink","domain":"centurylink.com","comment":"O&O inventory."},{"seller_id":81279,"seller_type":"PUBLISHER","name":"Toshiba","domain":"toshiba.com","comment":"O&O inventory."},{"seller_id":81303,"seller_type":"PUBLISHER","name":"Mediacom Communications Corp.","domain":"mediacomcable.com","comment":"O&O inventory."},{"seller_id":81307,"seller_type":"PUBLISHER","name":"Windstream Communications","domain":"windstream.com","comment":"O&O inventory."},{"seller_id":81309,"seller_type":"PUBLISHER","name":"Armstrong Wire","domain":"armstrongonewire.com","comment":"O&O inventory."},{"seller_id":81311,"seller_type":"PUBLISHER","name":"TDS Telecom","domain":"tdstelecom.com","comment":"O&O inventory."},{"seller_id":81313,"seller_type":"PUBLISHER","name":"WideOpenWest Finance, LLC","domain":"wowway.com","comment":"O&O inventory."},{"seller_id":81319,"seller_type":"PUBLISHER","name":"Cincinnati Bell Inc","domain":"cincinnatibell.com","comment":"O&O inventory."},{"seller_id":81321,"seller_type":"PUBLISHER","name":"Suddenlink Communications","domain":"suddenlink.com","comment":"O&O inventory."},{"seller_id":81323,"seller_type":"PUBLISHER","name":"Hughes Network Systems, LLC","domain":"hughesnet.com","comment":"O&O inventory."},{"seller_id":81325,"seller_type":"PUBLISHER","name":"Atlantic Broadband","domain":"atlanticbb.com","comment":"O&O inventory."},{"seller_id":81335,"seller_type":"PUBLISHER","name":"Grande Communications Networks, LLC.","domain":"mygrande.com","comment":"O&O inventory."},{"seller_id":81337,"seller_type":"PUBLISHER","name":"GVTC Communications","domain":"gvtc.com","comment":"O&O inventory."},{"seller_id":81341,"seller_type":"PUBLISHER","name":"Hawaiian Telcom","domain":"hawaiiantel.com","comment":"O&O inventory."},{"seller_id":81343,"seller_type":"PUBLISHER","name":"Atlantic Broadband","domain":"atlanticbb.com","comment":"O&O inventory."},{"seller_id":81347,"seller_type":"PUBLISHER","name":"TruVista","domain":"truvista.net","comment":"O&O inventory."},{"seller_id":81349,"seller_type":"PUBLISHER","name":"BendBroadband","domain":"bendbroadband.com","comment":"O&O inventory."},{"seller_id":81431,"seller_type":"PUBLISHER","name":"152 Media LLC","domain":"152media.com"},{"seller_id":81471,"seller_type":"PUBLISHER","name":"Penske Media Corporation","domain":"pmc.com"},{"seller_id":81475,"seller_type":"PUBLISHER","name":"GasBuddy LLC","domain":"gasbuddy.com"},{"seller_id":81479,"seller_type":"PUBLISHER","name":"Evolve Media LLC","domain":"evolvemediallc.com"},{"seller_id":81483,"seller_type":"INTERMEDIARY","name":"Division D","domain":"divisiond.com"},{"seller_id":81485,"seller_type":"PUBLISHER","name":"Gannett Satellite Information Network (USA Today)","domain":"gannett.com"},{"seller_id":81489,"seller_type":"PUBLISHER","name":"Earthlink","domain":"earthlink.net"},{"seller_id":81535,"seller_type":"PUBLISHER","name":"Wildtangent, Inc.","domain":"wildtangent.com"},{"seller_id":81539,"seller_type":"PUBLISHER","name":"Issuu Inc","domain":"issuu.com"},{"seller_id":81563,"seller_type":"PUBLISHER","name":"GSN Games","domain":"gsngames.com"},{"seller_id":81597,"seller_type":"PUBLISHER","name":"Olympia Media Group","domain":"theodysseyonline.com"},{"seller_id":81605,"seller_type":"PUBLISHER","name":"ZEDO, Inc.","domain":"zedo.com"},{"seller_id":81617,"seller_type":"PUBLISHER","name":"Marzen Media","domain":"fantasypros.com"},{"seller_id":81627,"seller_type":"PUBLISHER","name":"Factinate, LTD","domain":"factinate.com"},{"seller_id":81639,"seller_type":"PUBLISHER","name":"Future US Inc","domain":"futureplc.com"},{"seller_id":81671,"seller_type":"PUBLISHER","name":"Internet Brands Inc","domain":"internetbrands.com"},{"seller_id":81679,"seller_type":"PUBLISHER","name":"Covers Media Group Ltd","domain":"covers.com"},{"seller_id":81683,"seller_type":"PUBLISHER","name":"Accuradio, LLC","domain":"accuradio.com"},{"seller_id":81685,"seller_type":"INTERMEDIARY","name":"Brightcom Online Media Solutions","domain":"brightcom.com"},{"seller_id":81741,"seller_type":"PUBLISHER","name":"Lee Enterprises Inc.","domain":"lee.net"},{"seller_id":81749,"seller_type":"PUBLISHER","name":"Internet Brands Inc","domain":"internetbrands.com"},{"seller_id":81787,"seller_type":"INTERMEDIARY","name":"Alot Inc","domain":"inuvo.com"},{"seller_id":81789,"seller_type":"PUBLISHER","name":"Lola Digital Media, LLC","domain":"loladigitalmedia.com"},{"seller_id":81819,"seller_type":"PUBLISHER","name":"Sporcle, Inc.","domain":"sporcle.com"},{"seller_id":81858,"seller_type":"PUBLISHER","name":"Investing Channel Inc","domain":"investingchannel.com"},{"seller_id":81866,"seller_type":"PUBLISHER","name":"AT&T","domain":"att.com","comment":"O&O inventory."},{"seller_id":81867,"seller_type":"PUBLISHER","name":"Gray Television Group, Inc. (Raycom Media)","domain":"raycommedia.com"},{"seller_id":81871,"seller_type":"PUBLISHER","name":"Farlex, Inc.","domain":"farlex.com"},{"seller_id":81872,"seller_type":"PUBLISHER","name":"InsideHoops Media, Inc","domain":"InsideHoops.com"},{"seller_id":81877,"seller_type":"PUBLISHER","name":"WebMD Health Corp","domain":"webmd.com"},{"seller_id":81882,"seller_type":"PUBLISHER","name":"Media News Group Inc.","domain":"medianewsgroup.com"},{"seller_id":81891,"seller_type":"PUBLISHER","name":"Cantata Media, LLC","domain":"dailyvoice.com"},{"seller_id":81895,"seller_type":"PUBLISHER","name":"Allnurses.com, Inc","domain":"allnurses.com"},{"seller_id":81899,"seller_type":"PUBLISHER","name":"Tonwnews.com","domain":"townnews.com"},{"seller_id":81902,"seller_type":"INTERMEDIARY","name":"Cordless Media LLC","domain":"cordlessmedia.com"},{"seller_id":81914,"seller_type":"PUBLISHER","name":"Outdoor Hub, LLC","domain":"carbonmedia.com"},{"seller_id":81917,"seller_type":"PUBLISHER","name":"J Media Global, LLC","domain":"thejmg.com"},{"seller_id":81918,"seller_type":"PUBLISHER","name":"Nasdaq, Inc","domain":"nasdaq.com"},{"seller_id":81928,"seller_type":"PUBLISHER","name":"Vox Media, Inc","domain":"voxmedia.com"},{"seller_id":81929,"seller_type":"PUBLISHER","name":"Trusted Media Brands, Inc.","domain":"trustedmediabrands.com"},{"seller_id":81936,"seller_type":"PUBLISHER","name":"The New York Interconnect, LLC","domain":"nyinterconnect.com"},{"seller_id":81944,"seller_type":"PUBLISHER","name":"The Buffalo News, Inc.","domain":"buffalonews.com"},{"seller_id":81963,"seller_type":"PUBLISHER","name":"Boone Newspapers, Inc.","domain":"boonenewspapers.com"},{"seller_id":81965,"seller_type":"PUBLISHER","name":"Boat Group Holdings, Inc.","domain":"boatsgroup.com"},{"seller_id":81968,"seller_type":"PUBLISHER","name":"Drugsite Trust","domain":"drugs.com"},{"seller_id":81975,"seller_type":"PUBLISHER","name":"RCN Telecom Services, LLC.","domain":"rcn.com","comment":"O&O inventory."},{"seller_id":81985,"seller_type":"PUBLISHER","name":"BH Media Group Inc","domain":"bhmginc.com"},{"seller_id":81990,"seller_type":"PUBLISHER","name":"LifeZette Inc.","domain":"lifezette.com"},{"seller_id":81995,"seller_type":"PUBLISHER","name":"Fusion Media Limited","domain":"investing.com"},{"seller_id":81996,"seller_type":"PUBLISHER","name":"Barstool Sports Inc","domain":"barstoolsports.com"},{"seller_id":82012,"seller_type":"PUBLISHER","name":"TinyBeans USA LTD","domain":"tinybeans.com"},{"seller_id":82024,"seller_type":"PUBLISHER","name":"ABC National Television Sales Inc","domain":"abc.com"},{"seller_id":82030,"seller_type":"PUBLISHER","name":"Dex Media Inc (Yellow Pages)","domain":"dexyp.com"},{"seller_id":82037,"seller_type":"PUBLISHER","name":"Warner Bros Digital Networks Inc","domain":"warnerbros.com"},{"seller_id":82039,"seller_type":"PUBLISHER","name":"Integer Media LLC","domain":"publir.com"},{"seller_id":82043,"seller_type":"PUBLISHER","name":"NCC Media","domain":"nccmedia.com"},{"seller_id":82046,"seller_type":"PUBLISHER","name":"IR Media Ventures Corp","domain":"fatherly.com"},{"seller_id":82054,"seller_type":"PUBLISHER","name":"Urban Dictionary LLC","domain":"urbandictionary.com"},{"seller_id":82061,"seller_type":"PUBLISHER","name":"American Media Inc","domain":"americanmediainc.com"},{"seller_id":82062,"seller_type":"PUBLISHER","name":"VentureBeat, Inc","domain":"venturebeat.com"},{"seller_id":82069,"seller_type":"PUBLISHER","name":"SheMedia LLC","domain":"shemedia.com"},{"seller_id":82073,"seller_type":"PUBLISHER","name":"DoG Tech LLC","domain":"denofgeek.us"},{"seller_id":82077,"seller_type":"PUBLISHER","name":"Deseret Digital Media Inc.","domain":"deseretdigital.com"},{"seller_id":82078,"seller_type":"INTERMEDIARY","name":"Underdog Media LLC","domain":"udmserve.net"},{"seller_id":82079,"seller_type":"PUBLISHER","name":"Evite, Inc","domain":"evite.com"},{"seller_id":82080,"seller_type":"PUBLISHER","name":"Motorsport.com Inc.","domain":"motorsports.com"},{"seller_id":82081,"seller_type":"PUBLISHER","name":"Seattle Times Company","domain":"seattletimes.com"},{"seller_id":82083,"seller_type":"PUBLISHER","name":"College Spun Media Inc.","domain":"thespun.com"},{"seller_id":82085,"seller_type":"PUBLISHER","name":"123Greetings.com, Inc","domain":"123greetings-inc.com"},{"seller_id":82087,"seller_type":"PUBLISHER","name":"Whitepages Inc","domain":"whitepages.com"},{"seller_id":82092,"seller_type":"PUBLISHER","name":"BuzzFeed, Inc","domain":"buzzfeed.com"},{"seller_id":82093,"seller_type":"PUBLISHER","name":"MLB Advanced Media, L.P.","domain":"mlb.com"},{"seller_id":82095,"seller_type":"INTERMEDIARY","name":"Brightcom Online Media Solutions","domain":"brightcom.com"},{"seller_id":82101,"seller_type":"INTERMEDIARY","name":"SpringServe","domain":"springserve.com"},{"seller_id":82102,"seller_type":"PUBLISHER","name":"Say Media, Inc","domain":"saymedia.com"},{"seller_id":82103,"seller_type":"PUBLISHER","name":"Vila Media LLC","domain":"bobvila.com"},{"seller_id":82105,"seller_type":"INTERMEDIARY","name":"ZEDO, Inc.","domain":"zedo.com"},{"seller_id":82111,"seller_type":"PUBLISHER","name":"Phonearena EAD","domain":"phonearena.com"},{"seller_id":82112,"seller_type":"INTERMEDIARY","name":"Kiosked Information Systems Ltd","domain":"kiosked.com"},{"seller_id":82113,"seller_type":"PUBLISHER","name":"Vila Media LLC","domain":"bobvila.com"},{"seller_id":82115,"seller_type":"INTERMEDIARY","name":"Didna, Inc","domain":"didna.io"},{"seller_id":82124,"seller_type":"PUBLISHER","name":"Urban Dictionary LLC","domain":"urbandictionary.com"},{"seller_id":82128,"seller_type":"PUBLISHER","name":"EB Golf Media LLC","domain":"golf.com"},{"seller_id":82129,"seller_type":"INTERMEDIARY","name":"Insticator Inc.","domain":"insticator.com"},{"seller_id":82132,"seller_type":"PUBLISHER","name":"Voice Media Group, Inc","domain":"voicemediagroup.com"},{"seller_id":82134,"seller_type":"PUBLISHER","name":"Volantis Digital Media LLP","domain":"volantisdigital.com"},{"seller_id":82135,"seller_type":"INTERMEDIARY","name":"Volantis Digital Media LLP","domain":"volantisdigital.com"},{"seller_id":82141,"seller_type":"INTERMEDIARY","name":"PubWise, LLLP","domain":"pubwise.io"},{"seller_id":82146,"seller_type":"INTERMEDIARY","name":"Titan Gate AD","domain":"pubgalaxy.com"},{"seller_id":82151,"seller_type":"INTERMEDIARY","name":"GumGum","domain":"gumgum.com"},{"seller_id":82162,"seller_type":"INTERMEDIARY","name":"Publisher First ,Inc","domain":"freestar.com"},{"seller_id":82165,"seller_type":"PUBLISHER","name":"Lafayette Media Group LLC","domain":"lafayettemediagroup.com"},{"seller_id":82167,"seller_type":"PUBLISHER","name":"TravelingMom LLC","domain":"TravelingMom.com"},{"seller_id":82170,"seller_type":"PUBLISHER","name":"Microdigital Consulting Corporation","domain":"microdigitalmedia.com"},{"seller_id":82171,"seller_type":"BOTH","name":"AniView Inc","domain":"aniview.com"},{"seller_id":82173,"seller_type":"BOTH","name":"DANTOO LTD","domain":"dann2g.net"},{"seller_id":82176,"seller_type":"PUBLISHER","name":"BAMtech LLC","domain":"bamtechmedia.com"},{"seller_id":82177,"seller_type":"INTERMEDIARY","name":"Anyclip Ltd","domain":"anyclip.com"},{"seller_id":82185,"seller_type":"PUBLISHER","name":"Revolvy, LLC","domain":"revolvy.com"},{"seller_id":82186,"seller_type":"PUBLISHER","name":"National Review, Inc.","domain":"nationalreview.com"},{"seller_id":82187,"seller_type":"INTERMEDIARY","name":"The Publisher Desk, Inc.","domain":"publisherdesk.com"},{"seller_id":82188,"seller_type":"INTERMEDIARY","name":"PixFuture Media Inc.","domain":"pixfuture.com"},{"seller_id":82190,"seller_type":"INTERMEDIARY","name":"Integer  Media LLC","domain":"publir.com"},{"seller_id":82191,"seller_type":"INTERMEDIARY","name":"Acuity Ads Inc.","domain":"acuityads.com"},{"seller_id":82195,"seller_type":"PUBLISHER","name":"Ancient History Encyclopedia Limited","domain":"Ancient.eu"},{"seller_id":82197,"seller_type":"PUBLISHER","name":"Glam, Inc. dba BrideClick Inc","domain":"glam.com"},{"seller_id":82203,"seller_type":"PUBLISHER","name":"Investors Business Daily","domain":"investors.com"},{"seller_id":82204,"seller_type":"INTERMEDIARY","name":"VUUKLE DMCC","domain":"vuukle.com"},{"seller_id":82205,"seller_type":"PUBLISHER","name":"The Shade Room, LLC","domain":"theshaderoom.com"},{"seller_id":82206,"seller_type":"PUBLISHER","name":"NineOneFour Media LLC","domain":"nineonefourmedia.com"},{"seller_id":82210,"seller_type":"INTERMEDIARY","name":"Boldwin LTD","domain":"bold-win.com"},{"seller_id":82211,"seller_type":"PUBLISHER","name":"Rave inc","domain":"rave.io"},{"seller_id":82212,"seller_type":"PUBLISHER","name":"G-O Media Inc","domain":"g-omedia.com"},{"seller_id":82213,"seller_type":"PUBLISHER","name":"MOTOR TREND GROUP, LLC","domain":"motortrend.com"},{"seller_id":82216,"seller_type":"INTERMEDIARY","name":"Kubient Inc","domain":"kubient.com"},{"seller_id":82217,"seller_type":"INTERMEDIARY","name":"Kubient Inc","domain":"KUBIENT.COM"},{"seller_id":82218,"seller_type":"BOTH","name":"Adscend Media LLC","domain":"Adscend.com"},{"seller_id":82223,"seller_type":"PUBLISHER","name":"Townsquare Media, Inc","domain":"townsquaredigital.com"},{"seller_id":82224,"seller_type":"PUBLISHER","name":"VentureBeat Inc","domain":"venturebeat.com"},{"seller_id":82225,"seller_type":"PUBLISHER","name":"ExentTechnologiesLtd","domain":"exent.com"},{"seller_id":82226,"seller_type":"PUBLISHER","name":"Covers Media Group Limited","domain":"covers.com"},{"seller_id":82228,"seller_type":"PUBLISHER","name":"Dasco Interactive Inc","domain":"dascointeractive.com"},{"seller_id":82229,"seller_type":"PUBLISHER","name":"ABC National Television Sales Inc","domain":"abc.com"},{"seller_id":82231,"seller_type":"INTERMEDIARY","name":"Smart RTB LLC","domain":"smartrtb.com"},{"seller_id":82232,"seller_type":"INTERMEDIARY","name":"Snack Media Limited","domain":"snack-media.com"},{"seller_id":82233,"seller_type":"PUBLISHER","name":"Famous Birthdays LLC","domain":"famousbirthdays.com"},{"seller_id":82234,"seller_type":"PUBLISHER","name":"Centurylink","domain":"centurylink.com","comment":"O&O inventory"},{"seller_id":82235,"seller_type":"PUBLISHER","name":"Cantata Media LLC","domain":"dailyvoice.com"},{"seller_id":82236,"seller_type":"PUBLISHER","name":"Gleaner Company(Media)Limited","domain":"rjrgleanergroup.com"},{"seller_id":82237,"seller_type":"PUBLISHER","name":"Outreach Inc","domain":"outreachmediagroup.com"},{"seller_id":82239,"seller_type":"INTERMEDIARY","name":"Apester Ltd","domain":"apester.com"},{"seller_id":82240,"seller_type":"PUBLISHER","name":"FloSports Inc","domain":"flosports.tv"},{"seller_id":82243,"seller_type":"PUBLISHER","name":"The Daily Dot LLC","domain":"thedailydot.com"},{"seller_id":82245,"seller_type":"INTERMEDIARY","name":"Vidazoo Ltd","domain":"vidazoo.com"},{"seller_id":82250,"seller_type":"PUBLISHER","name":"Overwolf LTD","domain":"overwolf.com"},{"seller_id":82251,"seller_type":"PUBLISHER","name":"Automatad Inc","domain":"automatad.com"},{"seller_id":82252,"seller_type":"PUBLISHER","name":"Tradecraft LLC","domain":"mediatradecraft.com"},{"seller_id":82253,"seller_type":"PUBLISHER","name":"TDS Telcom","domain":"tds.net","comment":"O&O inventory"},{"seller_id":82254,"seller_type":"PUBLISHER","name":"Match Group Inc","domain":"match.com"},{"seller_id":82255,"seller_type":"PUBLISHER","name":"Slader LLC","domain":"slader.com"},{"seller_id":82256,"seller_type":"PUBLISHER","name":"Totally Her Media LLC","domain":"evolvemediallc.com"},{"seller_id":82257,"seller_type":"INTERMEDIARY","name":"Saambaa LLC","domain":"saambaa.com"},{"seller_id":82258,"seller_type":"PUBLISHER","name":"CraveOnline Media LLC","domain":"evolvemediallc.com"},{"seller_id":82259,"seller_type":"PUBLISHER","name":"Investing Channel Inc","domain":"Investingchannel.com"},{"seller_id":82264,"seller_type":"PUBLISHER","name":"Suth Media LLC","domain":"suthmedia.com"},{"seller_id":82266,"seller_type":"BOTH","name":"VidCrunch LLC","domain":"vidcrunch.com"},{"seller_id":82267,"seller_type":"PUBLISHER","name":"Suth Media LLC","domain":"suthmedia.com"},{"seller_id":82270,"seller_type":"PUBLISHER","name":"Cox Communications Inc","domain":"coxmedia.com"},{"seller_id":82272,"seller_type":"PUBLISHER","name":"Rough Maps Inc","domain":"roughmaps.com"},{"seller_id":82274,"seller_type":"PUBLISHER","name":"Urban Dictionary LLC","domain":"urbandictionary.com"},{"seller_id":82275,"seller_type":"INTERMEDIARY","name":"Zero1 Inc","domain":"vdo.ai"},{"seller_id":82277,"seller_type":"PUBLISHER","name":"Webcapacity Incorporated","domain":"wrestlinginc.com"},{"seller_id":82279,"seller_type":"PUBLISHER","name":"Al-Monitor LLC","domain":"almonitor.com"},{"seller_id":82282,"seller_type":"INTERMEDIARY","name":"Wise Publishing, Inc.","domain":"wisepublishing.com"},{"seller_id":82283,"seller_type":"PUBLISHER","name":"KueezEntertainmentLtd","domain":"kueez.com"},{"seller_id":82286,"seller_type":"INTERMEDIARY","name":"AAX LLC","domain":"aax.media"},{"seller_id":82287,"seller_type":"INTERMEDIARY","name":"bluTonic Inc","domain":"blutonic.com"},{"seller_id":82288,"seller_type":"INTERMEDIARY","name":"Amomama Media Limited","domain":"amomedia.com"},{"seller_id":82289,"seller_type":"INTERMEDIARY","name":"Revcontent Holdings Inc","domain":"revcontent.com"},{"seller_id":82290,"seller_type":"INTERMEDIARY","name":"Revcontent Holdings Inc","domain":"revcontent.com"},{"seller_id":82291,"seller_type":"INTERMEDIARY","name":"Engage BDR LLC","domain":"engagebdr.com"},{"seller_id":82292,"seller_type":"INTERMEDIARY","name":"Speroll Media Ltd","domain":"speroll.com"},{"seller_id":82293,"seller_type":"INTERMEDIARY","name":"Eklunds Hockey LLC","domain":"hockeybuzz.com"},{"seller_id":82294,"seller_type":"INTERMEDIARY","name":"Bentley Media Group LLC","domain":"bentleymediagroup.com"},{"seller_id":82296,"seller_type":"PUBLISHER","name":"Accuweather Inc","domain":"accuweather.com"},{"seller_id":82297,"seller_type":"INTERMEDIARY","name":"InvestorPlace Media, LLC","domain":"investorplace.com"},{"seller_id":82298,"seller_type":"INTERMEDIARY","name":"Pop Dust Inc","domain":"popdust.com"},{"seller_id":82299,"seller_type":"INTERMEDIARY","name":"Particle Media, Inc","domain":"newsbreak.com"},{"seller_id":82300,"seller_type":"INTERMEDIARY","name":"Vice Media LLC","domain":"vice.com"},{"seller_id":82301,"seller_type":"BOTH","name":"FreeStar","domain":"freestar.com"},{"seller_id":82302,"seller_type":"INTERMEDIARY","name":"Sportority Inc","domain":"minutemedia.com"}]}