{"contact_email":"info@firstimpression.io","contact_address":"24 Se'adya Ga'on Street, Tel Aviv, Israel, POB 20052!","version":"1.0","identifiers":[{"name":"TAG-ID","value":"a960877e77e58dd6"}],"sellers":[{"seller_id":23,"seller_type":"PUBLISHER","name":"Channel 9 Ltd"},{"seller_id":24,"seller_type":"PUBLISHER","name":"MegaPixel","domain":"megapixel.co.il"},{"seller_id":5042,"seller_type":"PUBLISHER","name":"MegaPixel","domain":"megapixel.co.il"},{"seller_id":5157,"seller_type":"PUBLISHER","is_confidential":1},{"seller_id":5269,"seller_type":"PUBLISHER","name":"Waylon H. Lewis Enterprises, LLC"},{"seller_id":5315,"seller_type":"INTERMEDIARY","name":"Web Wise House","domain":"web-wise.co.il"},{"seller_id":5319,"seller_type":"PUBLISHER","name":"Israel Today Newspaper Ltd.","domain":"israelhayom.co.il"},{"seller_id":5320,"seller_type":"PUBLISHER","name":"Israel Today Newspaper Ltd.","domain":"israelhayom.co.il"},{"seller_id":5334,"seller_type":"PUBLISHER","name":"Yediot Internet","domain":"ynet.co.il"},{"seller_id":5338,"seller_type":"PUBLISHER","name":"Haaretz Daily Newspaper Ltd","domain":"haaretz.co.il"},{"seller_id":5339,"seller_type":"PUBLISHER","name":"Haaretz Daily Newspaper Ltd","domain":"haaretz.co.il"},{"seller_id":5342,"seller_type":"INTERMEDIARY","name":"Zoomd"},{"seller_id":5343,"seller_type":"INTERMEDIARY","name":"Zoomd"},{"seller_id":5360,"seller_type":"PUBLISHER","name":"Migdor Ltd","domain":"mignews.com"},{"seller_id":5402,"seller_type":"INTERMEDIARY","name":"Notus Digital Media Group","domain":"notusdigital.com"},{"seller_id":5403,"seller_type":"INTERMEDIARY","name":"Notus Digital Media Group","domain":"notusdigital.com"},{"seller_id":5404,"seller_type":"INTERMEDIARY","name":"Notus Digital Media Group","domain":"notusdigital.com"},{"seller_id":5410,"seller_type":"INTERMEDIARY","name":"Notus Digital Media Group","domain":"notusdigital.com"},{"seller_id":5417,"seller_type":"INTERMEDIARY","name":"Notus Digital Media Group","domain":"notusdigital.com"},{"seller_id":5459,"seller_type":"PUBLISHER","name":"Zmanei Yisrael LTD","domain":"timesofisrael.com"},{"seller_id":5496,"seller_type":"PUBLISHER","name":"Insider News Group","domain":"business2community.com"},{"seller_id":5528,"seller_type":"INTERMEDIARY","name":"Notus Digital Media Group","domain":"notusdigital.com"},{"seller_id":5541,"seller_type":"INTERMEDIARY","name":"Notus Digital Media Group","domain":"notusdigital.com"},{"seller_id":5542,"seller_type":"INTERMEDIARY","name":"Notus Digital Media Group","domain":"notusdigital.com"},{"seller_id":5543,"seller_type":"INTERMEDIARY","name":"Notus Digital Media Group","domain":"notusdigital.com"},{"seller_id":5547,"seller_type":"INTERMEDIARY","name":"Notus Digital Media Group","domain":"notusdigital.com"},{"seller_id":5558,"seller_type":"PUBLISHER","name":"Zmanei Yisrael LTD","domain":"timesofisrael.com"},{"seller_id":5559,"seller_type":"PUBLISHER","name":"Reach PLC","domain":"reachplc.com"},{"seller_id":5632,"seller_type":"INTERMEDIARY","name":"J Media Group, LLC","domain":"thejmg.com"},{"seller_id":5712,"seller_type":"PUBLISHER","name":"923WPB LLC"},{"seller_id":5731,"seller_type":"PUBLISHER","name":"Code 9 Media, Inc.","domain":"code9media.com"},{"seller_id":5732,"seller_type":"PUBLISHER","name":"Code 9 Media, Inc.","domain":"code9media.com"},{"seller_id":5802,"seller_type":"PUBLISHER","name":"Jerusalem Post LTD","domain":"jpost.com"},{"seller_id":5811,"seller_type":"INTERMEDIARY","name":"MonetizeMore"},{"seller_id":5811,"seller_type":"PUBLISHER","name":"Fppt.com"},{"seller_id":5820,"seller_type":"PUBLISHER","name":"Prodigy Capital Holdings LLC"},{"seller_id":5828,"seller_type":"PUBLISHER","is_confidential":1},{"seller_id":5839,"seller_type":"INTERMEDIARY","name":"Notus Digital Media Group","domain":"notusdigital.com"},{"seller_id":5863,"seller_type":"PUBLISHER","name":"Fangraphs Inc","domain":"fangraphs.com"},{"seller_id":5890,"seller_type":"PUBLISHER","name":"Autobeef LLC","domain":"carcomplaints.com"},{"seller_id":5904,"seller_type":"INTERMEDIARY","name":"Notus Digital Media Group","domain":"notusdigital.com"},{"seller_id":5933,"seller_type":"INTERMEDIARY","name":"Notus Digital Media Group","domain":"notusdigital.com"},{"seller_id":5957,"seller_type":"PUBLISHER","name":"6Theory Media, LLC.","domain":"6theory.com"},{"seller_id":5958,"seller_type":"PUBLISHER","name":"6Theory Media, LLC.","domain":"6theory.com"},{"seller_id":5960,"seller_type":"PUBLISHER","name":"Two Plus Two Interactive, LLC"},{"seller_id":5971,"seller_type":"PUBLISHER","name":"Bleeping Computer, LLC.","domain":"bleepingcomputer.com"},{"seller_id":5976,"seller_type":"INTERMEDIARY","name":"Notus Digital Media Group","domain":"notusdigital.com"},{"seller_id":5995,"seller_type":"PUBLISHER","name":"Wikia, Inc.","domain":"fandom.com"},{"seller_id":5996,"seller_type":"PUBLISHER","name":"Code 9 Media, Inc.","domain":"code9media.com"},{"seller_id":6001,"seller_type":"PUBLISHER","name":"ESMG North America, Inc"},{"seller_id":6005,"seller_type":"PUBLISHER","name":"SALESBUTLERS UG"},{"seller_id":6009,"seller_type":"PUBLISHER","name":"Americanlisted Inc."},{"seller_id":6068,"seller_type":"PUBLISHER","is_confidential":1},{"seller_id":6070,"seller_type":"PUBLISHER","name":"Doctors Health Press Inc","domain":"doctorshealthpress.com"},{"seller_id":6078,"seller_type":"PUBLISHER","name":"Bondware, Inc","domain":"bondware.com"},{"seller_id":6087,"seller_type":"INTERMEDIARY","name":"Notus Digital Media Group","domain":"notusdigital.com"},{"seller_id":6088,"seller_type":"INTERMEDIARY","name":"Notus Digital Media Group","domain":"notusdigital.com"},{"seller_id":6095,"seller_type":"PUBLISHER","is_confidential":1},{"seller_id":6096,"seller_type":"INTERMEDIARY","name":"Notus Digital Media Group","domain":"notusdigital.com"},{"seller_id":6104,"seller_type":"PUBLISHER","name":"Grilling Guru Inc"},{"seller_id":6178,"seller_type":"INTERMEDIARY","name":"Notus Digital Media Group","domain":"notusdigital.com"},{"seller_id":6189,"seller_type":"PUBLISHER","is_confidential":1},{"seller_id":6233,"seller_type":"PUBLISHER","name":"Fansonline.net Ltd","domain":"fansonline.net"},{"seller_id":6247,"seller_type":"PUBLISHER","name":"NextPit GmbH"},{"seller_id":6250,"seller_type":"PUBLISHER","name":"NextPit GmbH"},{"seller_id":6251,"seller_type":"PUBLISHER","name":"NextPit GmbH"},{"seller_id":6252,"seller_type":"PUBLISHER","name":"NextPit GmbH"},{"seller_id":6253,"seller_type":"PUBLISHER","name":"NextPit GmbH"},{"seller_id":6254,"seller_type":"PUBLISHER","name":"NextPit GmbH"},{"seller_id":6262,"seller_type":"PUBLISHER","is_confidential":1},{"seller_id":6281,"seller_type":"PUBLISHER","name":"gayot.com"},{"seller_id":6282,"seller_type":"PUBLISHER","name":"Jubii A\/S"},{"seller_id":6287,"seller_type":"PUBLISHER","name":"IPN Digital"},{"seller_id":6292,"seller_type":"PUBLISHER","name":"VP Limited, LLC"},{"seller_id":6314,"seller_type":"PUBLISHER","name":"dailymail.co.uk"},{"seller_id":6316,"seller_type":"PUBLISHER","name":"Volare Novels"},{"seller_id":6351,"seller_type":"PUBLISHER","name":"Bright Mountain Media"},{"seller_id":6367,"seller_type":"INTERMEDIARY","name":"Notus Digital Media Group","domain":"notusdigital.com"},{"seller_id":6392,"seller_type":"PUBLISHER","name":"SparkPeople"},{"seller_id":6416,"seller_type":"PUBLISHER","name":"Yieldpeak"},{"seller_id":6426,"seller_type":"PUBLISHER","name":"Prime"},{"seller_id":6436,"seller_type":"PUBLISHER","name":"Quizz.biz"},{"seller_id":6442,"seller_type":"PUBLISHER","name":"Mingle"},{"seller_id":6458,"seller_type":"INTERMEDIARY","name":"Notus Digital Media Group","domain":"notusdigital.com"},{"seller_id":6477,"seller_type":"INTERMEDIARY","name":"Notus Digital Media Group","domain":"notusdigital.com"},{"seller_id":6481,"seller_type":"PUBLISHER","name":"Eurosport"},{"seller_id":6487,"seller_type":"PUBLISHER","name":"breakingmuscle.com"},{"seller_id":6493,"seller_type":"PUBLISHER","name":"Investing Channel"},{"seller_id":6494,"seller_type":"PUBLISHER","name":"Investing Channel"},{"seller_id":6495,"seller_type":"PUBLISHER","name":"Investing Channel"},{"seller_id":6505,"seller_type":"INTERMEDIARY","name":"Notus Digital Media Group","domain":"notusdigital.com"},{"seller_id":6506,"seller_type":"INTERMEDIARY","name":"Notus Digital Media Group","domain":"notusdigital.com"},{"seller_id":6507,"seller_type":"INTERMEDIARY","name":"Notus Digital Media Group","domain":"notusdigital.com"},{"seller_id":6509,"seller_type":"PUBLISHER","name":"Transfermarkt GmbH & Co. KG"},{"seller_id":6509,"seller_type":"PUBLISHER","name":"Perform Group"},{"seller_id":6512,"seller_type":"INTERMEDIARY","name":"Acqua Media"},{"seller_id":6514,"seller_type":"INTERMEDIARY","name":"Zoomd"},{"seller_id":6520,"seller_type":"PUBLISHER","name":"We Got This Covered, Inc.","domain":"wegotthiscovered.com"},{"seller_id":6521,"seller_type":"PUBLISHER","name":"Consumed Media"},{"seller_id":6525,"seller_type":"PUBLISHER","name":"Stiftung Radiomuseum Luzern"},{"seller_id":6526,"seller_type":"PUBLISHER","name":"Netlink"},{"seller_id":6526,"seller_type":"INTERMEDIARY","name":"Zoomd"},{"seller_id":6538,"seller_type":"INTERMEDIARY","name":"Notus Digital Media Group","domain":"notusdigital.com"},{"seller_id":6539,"seller_type":"PUBLISHER","name":"VGMods"},{"seller_id":6540,"seller_type":"PUBLISHER","name":"VGMods"},{"seller_id":6541,"seller_type":"PUBLISHER","name":"VGMods"},{"seller_id":6542,"seller_type":"PUBLISHER","name":"VGMods"},{"seller_id":6543,"seller_type":"PUBLISHER","name":"VGMods"},{"seller_id":6567,"seller_type":"INTERMEDIARY","name":"Notus Digital Media Group","domain":"notusdigital.com"},{"seller_id":6574,"seller_type":"PUBLISHER","name":"Asianfanfics"},{"seller_id":6590,"seller_type":"INTERMEDIARY","name":"Notus Digital Media Group","domain":"notusdigital.com"},{"seller_id":6592,"seller_type":"INTERMEDIARY","name":"Notus Digital Media Group","domain":"notusdigital.com"},{"seller_id":6593,"seller_type":"PUBLISHER","name":"Prime"},{"seller_id":6594,"seller_type":"PUBLISHER","name":"Prime"},{"seller_id":6595,"seller_type":"PUBLISHER","name":"Prime"},{"seller_id":6596,"seller_type":"PUBLISHER","name":"Prime"},{"seller_id":6597,"seller_type":"PUBLISHER","name":"Prime"},{"seller_id":6598,"seller_type":"PUBLISHER","name":"Prime"},{"seller_id":6599,"seller_type":"PUBLISHER","name":"Prime"},{"seller_id":6600,"seller_type":"PUBLISHER","name":"Prime"},{"seller_id":6603,"seller_type":"PUBLISHER","name":"Groupe Rustica"},{"seller_id":6605,"seller_type":"PUBLISHER","name":"Groupe Rustica"},{"seller_id":6620,"seller_type":"PUBLISHER","name":"Hemmings "},{"seller_id":6644,"seller_type":"PUBLISHER","name":"Attom Data"},{"seller_id":6647,"seller_type":"PUBLISHER","name":"Prime"},{"seller_id":6648,"seller_type":"PUBLISHER","name":"Prime"},{"seller_id":6649,"seller_type":"PUBLISHER","name":"Prime"},{"seller_id":6650,"seller_type":"PUBLISHER","name":"Prime"},{"seller_id":6651,"seller_type":"PUBLISHER","name":"Prime"},{"seller_id":6652,"seller_type":"PUBLISHER","name":"Prime"},{"seller_id":6653,"seller_type":"PUBLISHER","name":"Prime"},{"seller_id":6655,"seller_type":"PUBLISHER","name":"Prime"},{"seller_id":6656,"seller_type":"PUBLISHER","name":"Prime"},{"seller_id":6658,"seller_type":"PUBLISHER","name":"Prime"},{"seller_id":6659,"seller_type":"PUBLISHER","name":"Prime"},{"seller_id":6660,"seller_type":"PUBLISHER","name":"Prime"},{"seller_id":6661,"seller_type":"PUBLISHER","name":"Prime"},{"seller_id":6662,"seller_type":"PUBLISHER","name":"Prime"},{"seller_id":6673,"seller_type":"PUBLISHER","name":"TellyUpdates"},{"seller_id":6688,"seller_type":"PUBLISHER","name":"Investing Channel"},{"seller_id":6691,"seller_type":"PUBLISHER","name":"Jerusalem Post LTD","domain":"jpost.com"},{"seller_id":6692,"seller_type":"PUBLISHER","name":"Jerusalem Post LTD","domain":"jpost.com"},{"seller_id":6692,"seller_type":"PUBLISHER","name":"maariv.co.il - Mobile"},{"seller_id":6700,"seller_type":"PUBLISHER","name":"dumpaday.com"},{"seller_id":6714,"seller_type":"PUBLISHER","name":"Cofina"},{"seller_id":6738,"seller_type":"PUBLISHER","name":"tvguide.co.uk"},{"seller_id":6744,"seller_type":"INTERMEDIARY","name":"Zoomd"},{"seller_id":6746,"seller_type":"PUBLISHER","name":"Perform Group"},{"seller_id":6748,"seller_type":"INTERMEDIARY","name":"Acqua Media"},{"seller_id":6750,"seller_type":"INTERMEDIARY","name":"Notus Digital Media Group","domain":"notusdigital.com"},{"seller_id":6764,"seller_type":"INTERMEDIARY","name":"CyberMedia"},{"seller_id":6793,"seller_type":"PUBLISHER","name":"MusicMe"},{"seller_id":6796,"seller_type":"PUBLISHER","name":"uniontestprep.com"},{"seller_id":6799,"seller_type":"PUBLISHER","name":"Confidentielles"},{"seller_id":6800,"seller_type":"PUBLISHER","name":"Confidentielles"},{"seller_id":6801,"seller_type":"PUBLISHER","name":"Confidentielles"},{"seller_id":6803,"seller_type":"PUBLISHER","name":"Confidentielles"},{"seller_id":6811,"seller_type":"PUBLISHER","name":"Investing Channel"},{"seller_id":6814,"seller_type":"PUBLISHER","name":"Investing Channel"},{"seller_id":6815,"seller_type":"PUBLISHER","name":"Investing Channel"},{"seller_id":6816,"seller_type":"PUBLISHER","name":"Investing Channel"},{"seller_id":6846,"seller_type":"PUBLISHER","name":"Bellazon"},{"seller_id":6857,"seller_type":"PUBLISHER","name":"Groupe Rustica"},{"seller_id":6888,"seller_type":"PUBLISHER","name":"Tribe Web"},{"seller_id":6898,"seller_type":"PUBLISHER","name":"Investing Channel"},{"seller_id":6899,"seller_type":"PUBLISHER","name":"Investing Channel"},{"seller_id":6948,"seller_type":"PUBLISHER","name":"Perform Group"},{"seller_id":6950,"seller_type":"PUBLISHER","name":"News18"},{"seller_id":6956,"seller_type":"PUBLISHER","name":"Haaretz Daily Newspaper Ltd","domain":"haaretz.co.il"},{"seller_id":6962,"seller_type":"PUBLISHER","name":"Walla"},{"seller_id":6963,"seller_type":"PUBLISHER","name":"Perform Group"},{"seller_id":6964,"seller_type":"PUBLISHER","name":"Perform Group"},{"seller_id":6968,"seller_type":"PUBLISHER","name":"Skymods"},{"seller_id":7024,"seller_type":"PUBLISHER","name":"roleplayer.me"},{"seller_id":7025,"seller_type":"PUBLISHER","name":"AniRolePlay.com"},{"seller_id":7031,"seller_type":"PUBLISHER","name":"RolePlay.me"},{"seller_id":7051,"seller_type":"PUBLISHER","name":"GSMArena"},{"seller_id":7066,"seller_type":"PUBLISHER","name":"Yad2"},{"seller_id":7071,"seller_type":"PUBLISHER","name":"Yieldpeak"},{"seller_id":7075,"seller_type":"PUBLISHER","name":"Playbill"},{"seller_id":7097,"seller_type":"PUBLISHER","name":"OBJ Digital"},{"seller_id":7099,"seller_type":"PUBLISHER","name":"Gamezop"},{"seller_id":7103,"seller_type":"PUBLISHER","name":"P&P Vegas Group"},{"seller_id":7121,"seller_type":"PUBLISHER","name":"makorrishon.co.il"},{"seller_id":7127,"seller_type":"PUBLISHER","name":"MyNet"},{"seller_id":7137,"seller_type":"PUBLISHER","name":"Young Hollywood"},{"seller_id":7162,"seller_type":"PUBLISHER","name":"TestYourBond.com"},{"seller_id":7165,"seller_type":"INTERMEDIARY","name":"Notus Digital Media Group","domain":"notusdigital.com"},{"seller_id":7166,"seller_type":"INTERMEDIARY","name":"Notus Digital Media Group","domain":"notusdigital.com"},{"seller_id":7171,"seller_type":"PUBLISHER","name":"JunkMail"},{"seller_id":7172,"seller_type":"PUBLISHER","name":"Jobsflag.com"},{"seller_id":7173,"seller_type":"PUBLISHER","name":"Yieldpeak"},{"seller_id":7175,"seller_type":"PUBLISHER","name":"CultureHook"},{"seller_id":7193,"seller_type":"PUBLISHER","name":"Horoscopes"},{"seller_id":7211,"seller_type":"PUBLISHER","name":"Young Hollywood"},{"seller_id":7218,"seller_type":"INTERMEDIARY","name":"Notus Digital Media Group","domain":"notusdigital.com"},{"seller_id":7219,"seller_type":"PUBLISHER","name":"Wikia, Inc.","domain":"fandom.com"},{"seller_id":7220,"seller_type":"PUBLISHER","name":"Schlock Mercenary"},{"seller_id":7226,"seller_type":"INTERMEDIARY","name":"Notus Digital Media Group","domain":"notusdigital.com"},{"seller_id":7233,"seller_type":"PUBLISHER","name":"gogy.com"},{"seller_id":7241,"seller_type":"INTERMEDIARY","name":"Notus Digital Media Group","domain":"notusdigital.com"},{"seller_id":7242,"seller_type":"INTERMEDIARY","name":"Notus Digital Media Group","domain":"notusdigital.com"},{"seller_id":7246,"seller_type":"PUBLISHER","name":"United Vertical Media GmbH"},{"seller_id":7249,"seller_type":"PUBLISHER","name":"Ultrasurf.us"},{"seller_id":7253,"seller_type":"PUBLISHER","name":"Daily Caller"},{"seller_id":7256,"seller_type":"PUBLISHER","name":"Elokence"},{"seller_id":7267,"seller_type":"PUBLISHER","name":"Let's Run"},{"seller_id":7268,"seller_type":"PUBLISHER","name":"m.gogy.com"},{"seller_id":7269,"seller_type":"PUBLISHER","name":"Haaretz Daily Newspaper Ltd","domain":"haaretz.co.il"},{"seller_id":7272,"seller_type":"PUBLISHER","name":"Netpoint-Media"},{"seller_id":7274,"seller_type":"PUBLISHER","name":"SnackMedia"},{"seller_id":7290,"seller_type":"INTERMEDIARY","name":"Notus Digital Media Group","domain":"notusdigital.com"},{"seller_id":7291,"seller_type":"INTERMEDIARY","name":"Notus Digital Media Group","domain":"notusdigital.com"},{"seller_id":7293,"seller_type":"INTERMEDIARY","name":"Notus Digital Media Group","domain":"notusdigital.com"},{"seller_id":7295,"seller_type":"PUBLISHER","name":"Journalistenwatch e.V."},{"seller_id":7296,"seller_type":"PUBLISHER","name":"Jerusalem Post LTD","domain":"jpost.com"},{"seller_id":7297,"seller_type":"PUBLISHER","name":"Yieldpeak"},{"seller_id":7300,"seller_type":"PUBLISHER","name":"SimFileShare Ltd"},{"seller_id":7301,"seller_type":"PUBLISHER","name":"Melon Reklam"},{"seller_id":7302,"seller_type":"INTERMEDIARY","name":"Notus Digital Media Group","domain":"notusdigital.com"},{"seller_id":7309,"seller_type":"PUBLISHER","name":"MocoSpace"},{"seller_id":7325,"seller_type":"INTERMEDIARY","name":"Notus Digital Media Group","domain":"notusdigital.com"},{"seller_id":7326,"seller_type":"PUBLISHER","name":"DesiSerials"},{"seller_id":7330,"seller_type":"PUBLISHER","name":"Yieldpeak"},{"seller_id":7349,"seller_type":"PUBLISHER","name":"Code 9 Media, Inc.","domain":"code9media.com"},{"seller_id":7359,"seller_type":"PUBLISHER","name":"Yieldpeak"},{"seller_id":7362,"seller_type":"INTERMEDIARY","name":"SetupAd"},{"seller_id":7365,"seller_type":"INTERMEDIARY","name":"Notus Digital Media Group","domain":"notusdigital.com"},{"seller_id":7366,"seller_type":"INTERMEDIARY","name":"Notus Digital Media Group","domain":"notusdigital.com"},{"seller_id":7374,"seller_type":"PUBLISHER","name":"Yieldpeak"},{"seller_id":7380,"seller_type":"INTERMEDIARY","name":"Notus Digital Media Group","domain":"notusdigital.com"},{"seller_id":7383,"seller_type":"INTERMEDIARY","name":"Notus Digital Media Group","domain":"notusdigital.com"},{"seller_id":7385,"seller_type":"INTERMEDIARY","name":"Notus Digital Media Group","domain":"notusdigital.com"},{"seller_id":7392,"seller_type":"INTERMEDIARY","name":"SetupAd"},{"seller_id":7398,"seller_type":"INTERMEDIARY","name":"Notus Digital Media Group","domain":"notusdigital.com"},{"seller_id":7403,"seller_type":"INTERMEDIARY","name":"SetupAd"},{"seller_id":7411,"seller_type":"PUBLISHER","name":"Oodle"},{"seller_id":7419,"seller_type":"INTERMEDIARY","name":"SetupAd"},{"seller_id":7421,"seller_type":"PUBLISHER","name":"24\/7 Wall St., LLC"},{"seller_id":7441,"seller_type":"PUBLISHER","name":"filehippo.com"},{"seller_id":7443,"seller_type":"INTERMEDIARY","name":"Notus Digital Media Group","domain":"notusdigital.com"},{"seller_id":7445,"seller_type":"INTERMEDIARY","name":"Notus Digital Media Group","domain":"notusdigital.com"},{"seller_id":7461,"seller_type":"PUBLISHER","name":"Business Advertising"},{"seller_id":7467,"seller_type":"PUBLISHER","name":"Rent.com.au"},{"seller_id":7470,"seller_type":"PUBLISHER","name":"Honolulu Star-Advertiser"},{"seller_id":7760,"seller_type":"PUBLISHER","name":"PenPal World"},{"seller_id":7762,"seller_type":"INTERMEDIARY","name":"SetupAd"},{"seller_id":7765,"seller_type":"PUBLISHER","name":"Alright Media"},{"seller_id":7778,"seller_type":"PUBLISHER","name":"Greynium Information Technologies"},{"seller_id":7779,"seller_type":"PUBLISHER","name":"Greynium Information Technologies"},{"seller_id":7780,"seller_type":"PUBLISHER","name":"Greynium Information Technologies"},{"seller_id":7781,"seller_type":"PUBLISHER","name":"Greynium Information Technologies"},{"seller_id":7782,"seller_type":"PUBLISHER","name":"Greynium Information Technologies"},{"seller_id":7783,"seller_type":"PUBLISHER","name":"Greynium Information Technologies"},{"seller_id":7787,"seller_type":"PUBLISHER","name":"Yediot Internet","domain":"ynet.co.il"},{"seller_id":7790,"seller_type":"PUBLISHER","name":"JunkMail"},{"seller_id":7797,"seller_type":"PUBLISHER","name":"IPN Digital"},{"seller_id":7801,"seller_type":"PUBLISHER","name":"Khaleej Times"},{"seller_id":7802,"seller_type":"PUBLISHER","name":"Samnytt.se"},{"seller_id":7804,"seller_type":"INTERMEDIARY","name":"Zoomd"},{"seller_id":7805,"seller_type":"INTERMEDIARY","name":"Zoomd"},{"seller_id":7806,"seller_type":"INTERMEDIARY","name":"Zoomd"},{"seller_id":7815,"seller_type":"PUBLISHER","name":"Singletrack"},{"seller_id":7819,"seller_type":"PUBLISHER","name":"DesiSerials"},{"seller_id":7829,"seller_type":"PUBLISHER","name":"Hive Media"},{"seller_id":7837,"seller_type":"PUBLISHER","name":"The Mandy Network"},{"seller_id":7852,"seller_type":"INTERMEDIARY","name":"Zoomd"},{"seller_id":7884,"seller_type":"PUBLISHER","name":"OBJ Digital"},{"seller_id":7887,"seller_type":"PUBLISHER","name":"Yieldpeak"},{"seller_id":7896,"seller_type":"PUBLISHER","name":"PeopleFinders"}]}